MANIFEST.in
README.md
setup.py
leoid/__init__.py
leoid/leoid.py
leoid/stage_1.pkl
leoid/stage_2.pkl
leoid.egg-info/PKG-INFO
leoid.egg-info/SOURCES.txt
leoid.egg-info/dependency_links.txt
leoid.egg-info/requires.txt
leoid.egg-info/top_level.txt